totalsize/__init__.py
totalsize/total.py
totalsize-0.7.2.dist-info/entry_points.txt
totalsize-0.7.2.dist-info/LICENSE
totalsize-0.7.2.dist-info/WHEEL
totalsize-0.7.2.dist-info/METADATA
totalsize-0.7.2.dist-info/RECORD
