Metadata-Version: 2.1
Name: totalsize
Version: 0.7.2
Summary: Totalsize uses yt-dlp to calculate total size of all videos in a playlist
Author-email: theychx <theychx@fastmail.com>
Requires-Python: >=3.6
Classifier: License :: OSI Approved :: MIT License
Classifier: Development Status :: 3 - Alpha
Classifier: Programming Language :: Python :: 3
Classifier: Programming Language :: Python :: 3.6
Classifier: Programming Language :: Python :: 3.7
Classifier: Programming Language :: Python :: 3.8
Classifier: Programming Language :: Python :: 3.9
Classifier: Programming Language :: Python :: 3.10
Classifier: Topic :: Multimedia
Classifier: Topic :: Multimedia :: Sound/Audio
Classifier: Topic :: Multimedia :: Video
Requires-Dist: yt-dlp >=2022.5.18
Requires-Dist: prettytable >=3.3.0
Project-URL: Home, https://github.com/theychx/totalsize
